Fast_Profiling_UI/Missing.py
Fast_Profiling_UI/Overview.py
Fast_Profiling_UI/Sample.py
Fast_Profiling_UI/Variables.py
Fast_Profiling_UI/__init__.py
Fast_Profiling_UI-0.3.dist-info/METADATA
Fast_Profiling_UI-0.3.dist-info/WHEEL
Fast_Profiling_UI-0.3.dist-info/top_level.txt
Fast_Profiling_UI-0.3.dist-info/RECORD
