Metadata-Version: 2.1
Name: Fast_Profiling_UI
Version: 0.3
Summary: An Exploratory Data Analysis Package for Data Engineers With UI
Author: Mukesh
Keywords: python,pandas,numpy,tkinter,eda,data analysis
Classifier: Development Status :: 1 - Planning
Classifier: Intended Audience :: Developers
Classifier: Intended Audience :: Science/Research
Classifier: Programming Language :: Python :: 3
Classifier: Operating System :: OS Independent
Classifier: License :: OSI Approved :: MIT License
Classifier: Topic :: Software Development :: Libraries :: Python Modules
Requires-Python: >=3.6
Requires-Dist: pandas
Requires-Dist: numpy
